link_pty/__init__.py
link_pty/terminal_manager.py
link_pty-0.7.0.dist-info/LICENSE
link_pty-0.7.0.dist-info/METADATA
link_pty-0.7.0.dist-info/WHEEL
link_pty-0.7.0.dist-info/entry_points.txt
link_pty-0.7.0.dist-info/top_level.txt
link_pty-0.7.0.dist-info/RECORD
