Metadata-Version: 2.1
Name: link-pty
Version: 0.7.0
Summary: A package to manage pseudo terminals via WebSocket
Home-page: https://github.com/ricepastem/link_pty
Author: ricepastem
License: UNKNOWN
Platform: UNKNOWN
Classifier: Programming Language :: Python :: 3
Classifier: License :: OSI Approved :: MIT License
Classifier: Operating System :: OS Independent
Requires-Python: >=3.6
License-File: LICENSE
Requires-Dist: websockets
Requires-Dist: requests
Requires-Dist: psutil
